odoo/addons/product_state_stock_base/README.rst
odoo/addons/product_state_stock_base/__init__.py
odoo/addons/product_state_stock_base/__manifest__.py
odoo/addons/product_state_stock_base/i18n/it.po
odoo/addons/product_state_stock_base/i18n/product_state_stock_base.pot
odoo/addons/product_state_stock_base/readme/CONTRIBUTORS.md
odoo/addons/product_state_stock_base/readme/CREDITS.md
odoo/addons/product_state_stock_base/readme/DESCRIPTION.md
odoo/addons/product_state_stock_base/readme/USAGE.md
odoo/addons/product_state_stock_base/security/security.xml
odoo/addons/product_state_stock_base/static/description/icon.png
odoo/addons/product_state_stock_base/static/description/index.html
odoo/addons/product_state_stock_base/views/product_state_views.xml
odoo_addon_product_state_stock_base-18.0.1.0.0.4.dist-info/METADATA
odoo_addon_product_state_stock_base-18.0.1.0.0.4.dist-info/WHEEL
odoo_addon_product_state_stock_base-18.0.1.0.0.4.dist-info/top_level.txt
odoo_addon_product_state_stock_base-18.0.1.0.0.4.dist-info/RECORD
